{
  "configurations": [
    {
      "directories": [
        {
          "build": ".",
          "minimumCMakeVersion": {
            "string": "3.4.1"
          },
          "projectIndex": 0,
          "source": ".",
          "targetIndexes": [
            0
          ]
        }
      ],
      "name": "Debug",
      "projects": [
        {
          "directoryIndexes": [
            0
          ],
          "name": "Project",
          "targetIndexes": [
            0
          ]
        }
      ],
      "targets": [
        {
          "directoryIndex": 0,
          "id": "native_keys::@6890427a1f51a3e7e1df",
          "jsonFile": "target-native_keys-Debug-6d053459c12a59bdca24.json",
          "name": "native_keys",
          "projectIndex": 0
        }
      ]
    }
  ],
  "kind": "codemodel",
  "paths": {
    "build": "/Users/mobileapp/AndroidStudioProjects/easy-app/native_keys/android/.cxx/Debug/17t1s1j3/x86_64",
    "source": "/Users/mobileapp/AndroidStudioProjects/easy-app/native_keys/android"
  },
  "version": {
    "major": 2,
    "minor": 1
  }
}
